AUTHORS
ChangeLog
LICENSE
MANIFEST.in
Makefile
README.rst
_60_tuskar_boxes.py.example
_60_tuskar_sat_ui.py.example
manage.py
requirements.txt
run_tests.sh
setup.cfg
setup.py
test-requirements.txt
tox.ini
doc/Makefile
doc/make.bat
doc/source/conf.py
doc/source/index.rst
doc/source/install.rst
test/__init__.py
test/selenium.py
test/settings.py
test/enabled/_60_tuskar_boxes.py
test/enabled/_60_tuskar_sat_ui.py
test/enabled/__init__.py
tools/install_venv.py
tools/with_venv.sh
tuskar_boxes/__init__.py
tuskar_boxes/overview/__init__.py
tuskar_boxes/overview/forms.py
tuskar_boxes/overview/panel.py
tuskar_boxes/overview/tests.py
tuskar_boxes/overview/urls.py
tuskar_boxes/overview/views.py
tuskar_boxes/static/tuskar_boxes/js/tuskar.boxes.js
tuskar_boxes/static/tuskar_boxes/js/tuskar.boxes_progress.js
tuskar_boxes/static/tuskar_boxes/scss/tuskar_boxes.scss
tuskar_boxes/static/tuskar_boxes/tests/tuskar.boxes.js
tuskar_boxes/static/tuskar_boxes/tests/tuskar.boxes_progress.js
tuskar_boxes/templates/tuskar_boxes/qunit.html
tuskar_boxes/templates/tuskar_boxes/overview/_global_service_config.html
tuskar_boxes/templates/tuskar_boxes/overview/_node_info.html
tuskar_boxes/templates/tuskar_boxes/overview/_node_info_js.html
tuskar_boxes/templates/tuskar_boxes/overview/_role_info.html
tuskar_boxes/templates/tuskar_boxes/overview/global_service_config.html
tuskar_boxes/templates/tuskar_boxes/overview/index.html
tuskar_boxes/templates/tuskar_boxes/overview/role_nodes_edit.html
tuskar_boxes/templates/tuskar_boxes/overview/role_nodes_live.html
tuskar_boxes/templates/tuskar_boxes/overview/role_nodes_status.html
tuskar_sat_ui/__init__.py
tuskar_sat_ui/models.py
tuskar_sat_ui/nodes/__init__.py
tuskar_sat_ui/nodes/panel.py
tuskar_sat_ui/nodes/tables.py
tuskar_sat_ui/nodes/tabs.py
tuskar_sat_ui/nodes/tests.py
tuskar_sat_ui/nodes/urls.py
tuskar_sat_ui/nodes/views.py
tuskar_sat_ui/templates/infrastructure/nodes/_detail_overview_sat.html
tuskar_ui_extras.egg-info/PKG-INFO
tuskar_ui_extras.egg-info/SOURCES.txt
tuskar_ui_extras.egg-info/dependency_links.txt
tuskar_ui_extras.egg-info/not-zip-safe
tuskar_ui_extras.egg-info/pbr.json
tuskar_ui_extras.egg-info/requires.txt
tuskar_ui_extras.egg-info/top_level.txt